app/__init__.py
app/__main__.py
app/cli.py
app/src/__init__.py
app/src/mclib/__init__.py
app/src/mclib/mclib.py
app/src/profiles/__init__.py
app/src/profiles/profileManagement.py
app/src/screens/DashboardScreen.py
app/src/screens/ProfilesScreen.py
app/src/screens/__init__.py
app/src/styles/Styles.py
app/src/themes/__init__.py
app/src/themes/themes.py
app/src/utils/__init__.py
app/src/utils/fileHandling.py
app/src/utils/miscFunctions.py
app/src/utils/typo.py
kaleido_launcher-0.0.4.dist-info/licenses/LICENSE
kaleido_launcher-0.0.4.dist-info/METADATA
kaleido_launcher-0.0.4.dist-info/WHEEL
kaleido_launcher-0.0.4.dist-info/entry_points.txt
kaleido_launcher-0.0.4.dist-info/top_level.txt
kaleido_launcher-0.0.4.dist-info/RECORD
