Metadata-Version: 2.4
Name: kaleido-launcher
Version: 0.0.4
Summary: TUI launcher for Minecraft profiles with Textual
Author-email: Cristian Manuel de Leon Monzon <cristiandeleonmonzon@gmail.com>
Maintainer-email: Cristian Manuel de Leon Monzon <cristiandeleonmonzon@gmail.com>
License: MIT
Requires-Python: <=3.14.2,>=3.10
License-File: LICENSE
Requires-Dist: aiohttp>=3.13.3
Requires-Dist: build>=1.4.0
Requires-Dist: minecraft-launcher-lib>=8.0
Requires-Dist: pydantic>=2.12.5
Requires-Dist: pyinstaller>=6.18.0
Requires-Dist: textual>=7.4.0
Requires-Dist: textual-dev>=1.8.0
Requires-Dist: twine>=6.2.0
Dynamic: license-file
